{
    "version": "fb738d5326c0f002d26fa672c8582b7949c4fe38",
    "description": "A Deezer downloader built from the ashes of Deezloader Remix.",
    "homepage": "https://deemix.app/",
    "license": "GPL-3.0-or-later",
    "url": "https://download.deemix.app/gui/win-amd64-latest.exe",
    "hash": "48c3308e9f79864ed67268ef5539ccaeae702ad4d6708d2b7fa6d1f54e141ef0",
    "bin": "win-amd64-latest.exe",
    "shortcuts": [
        [
            "win-amd64-latest.exe",
            "deemix"
        ]
    ],
    "checkver": {
        "url": "https://gitlab.com/api/v4/projects/RemixDev%2Fdeemix-gui/repository/commits",
        "jp": "$[0].id"
    },
    "autoupdate": {
        "url": "https://download.deemix.app/gui/win-amd64-latest.exe",
        "hash": "$url.sha256"
    }
}
