{
    "version": "N-100141-g14458f2939-g87c1b74233+3",
    "description": "A complete, cross-platform solution to record, convert and stream audio and video.",
    "homepage": "https://ffmpeg.org",
    "license": "GPL-3.0-or-later",
    "url": "https://jeremylee.sh/data/bin/ffmpeg.7z",
    "hash": "69ff5d75471b68261074a90f1d49790d7c34c3bab2ef4abc649c4adda6b1da75",
    "bin": "ffmpeg.exe",
    "checkver": {
        "url": "https://jeremylee.sh/bin.html",
        "regex": "</span><span class=\"db\">(.*?)<\\/span>"
    },
    "autoupdate": {
        "url": "https://jeremylee.sh/data/bin/ffmpeg.7z",
        "hash": "$url.sha256"
    }
}
