{
    "version": "2.0.15",
    "description": "Single-file distributable web server.",
    "homepage": "https://redbean.dev/",
    "license": "ISC",
    "url": "https://redbean.dev/redbean-demo-2.0.15.com#/redbean.com",
    "hash": "fe21d5deae1c54b120086818016197f16f2a7345d08a98ae69f08eefd5d8c41c",
    "bin": "redbean.com",
    "shortcuts": [
        [
            "redbean.com",
            "redbean"
        ]
    ],
    "checkver": {
        "url": "https://redbean.dev/",
        "regex": "redbean-([\\d.]+).com"
    },
    "autoupdate": {
        "url": "https://redbean.dev/redbean-demo-$version.com#/redbean.com",
        "hash": "$url.sha256"
    }
}
